MANIFEST.in
README.rst
setup.py
odt_templater/__init__.py
odt_templater.egg-info/PKG-INFO
odt_templater.egg-info/SOURCES.txt
odt_templater.egg-info/dependency_links.txt
odt_templater.egg-info/not-zip-safe
odt_templater.egg-info/top_level.txt