Metadata-Version: 1.0
Name: odt-templater
Version: 0.1.1
Summary: Simple Open Document Text templating tool
Home-page: http://github.com/BjarniRunar/odt_templater
Author: Bjarni R. Einarsson
Author-email: bre@klaki.net
License: MIT
Platform: UNKNOWN
